[{"Date": "2020-12-31", "Ticker": "PII", "Senator": "Capito, Shelley Moore", "Transaction": "Sale", "Amount": 1001.0, "Range": "$1,001 - $15,000"}, {"Date": "2018-04-24", "Ticker": "PII", "Senator": "Capito, Shelley Moore", "Transaction": "Purchase", "Amount": 1001.0, "Range": "$1,001 - $15,000"}, {"Date": "2018-04-24", "Ticker": "PII", "Senator": "Capito, Shelley Moore", "Transaction": "Purchase", "Amount": 1001.0, "Range": "$1,001 - $15,000"}, {"Date": "2018-04-05", "Ticker": "PII", "Senator": "Capito, Shelley Moore", "Transaction": "Purchase", "Amount": 1001.0, "Range": "$1,001 - $15,000"}, {"Date": "2018-04-05", "Ticker": "PII", "Senator": "Capito, Shelley Moore", "Transaction": "Purchase", "Amount": 1001.0, "Range": "$1,001 - $15,000"}]